geoquanta/__init__.py
geoquanta/common.py
geoquanta/geoquanta.py
geoquanta/utils.py
geoquanta-0.0.5.dist-info/LICENSE
geoquanta-0.0.5.dist-info/METADATA
geoquanta-0.0.5.dist-info/WHEEL
geoquanta-0.0.5.dist-info/entry_points.txt
geoquanta-0.0.5.dist-info/top_level.txt
geoquanta-0.0.5.dist-info/RECORD
